[
{ "text": "말을 적는 기호", "hint": "글자" },
{ "text": "머리에 쓰는 것", "hint": "모자" },
{ "text": "발에 신는 딱딱한 신발", "hint": "구두" },
{ "text": "지구 밖의 넓은 공간", "hint": "우주" },
{ "text": "구름이 많은 날씨", "hint": "흐림" },
{ "text": "나무로 댐을 만드는 동물", "hint": "비버" },
{ "text": "길고 초록색인 채소", "hint": "파" },
{ "text": "추운 날 단단하게 얼은 모양", "hint": "꽁꽁" },
{ "text": "벼가 자라는 물이 잠긴 땅", "hint": "논" },
{ "text": "손에 들고 바람을 일으키는 도구", "hint": "부채" },
{ "text": "귀하고 값진 물건", "hint": "보물" },
{ "text": "귀로 듣는 것", "hint": "소리" },
{ "text": "숟가락과 젓가락", "hint": "수저" },
{ "text": "잎이나 꽃을 우려내어 마시는 따뜻한 물", "hint": "차" },
{ "text": "보글보글 끓인 국물이 있는 음식", "hint": "찌개" },
{ "text": "시간을 알려준다", "hint": "시계" },
{ "text": "나와 너", "hint": "우리" },
{ "text": "가늘게 부순 것", "hint": "가루" },
{ "text": "ㄱ의 이름", "hint": "기역" }
]
